morsetune/__init__.py
morsetune/morsetune.py
morsetune/tests/test_tune.py
morsetune-0.1.5.dist-info/licenses/LICENSE
morsetune-0.1.5.dist-info/METADATA
morsetune-0.1.5.dist-info/WHEEL
morsetune-0.1.5.dist-info/top_level.txt
morsetune-0.1.5.dist-info/RECORD
